glrp/VERSION
glrp/__init__.py
glrp/__main__.py
glrp/cli.py
glrp/compare.py
glrp/internal_parser.py
glrp/pretty.py
glrp/summary.py
glrp/utils.py
glrp/version.py
glrp-0.3.3.dist-info/licenses/LICENSE
glrp-0.3.3.dist-info/METADATA
glrp-0.3.3.dist-info/WHEEL
glrp-0.3.3.dist-info/entry_points.txt
glrp-0.3.3.dist-info/top_level.txt
glrp-0.3.3.dist-info/RECORD
