Metadata-Version: 2.4
Name: glrp
Version: 0.3.3
Summary: Parser for git log --raw
Home-page: https://github.com/olehermanse/glrp
Author: Ole Herman Schumacher Elgesem
Author-email: 
Classifier: Programming Language :: Python :: 3
Classifier: License :: OSI Approved :: MIT License
Classifier: Operating System :: OS Independent
Requires-Python: >=3.10
License-File: LICENSE
Dynamic: author
Dynamic: classifier
Dynamic: description
Dynamic: description-content-type
Dynamic: home-page
Dynamic: license-file
Dynamic: requires-python
Dynamic: summary
